bt_decode-0.6.0.dist-info/METADATA
bt_decode-0.6.0.dist-info/WHEEL
bt_decode-0.6.0.dist-info/licenses/LICENSE
bt_decode/__init__.py
bt_decode/__init__.pyi
bt_decode/py.typed
bt_decode/bt_decode.cp313-win_amd64.pyd
bt_decode-0.6.0.dist-info/RECORD
